Metadata-Version: 2.1
Name: vulcan-sql
Version: 0.8.0
Summary: VulcanSQL turns your SQL templates into data APIs for efficient data sharing. No backend skills required. Empower your data sharing, faster.
Home-page: https://github.com/Canner/vulcan-sql
Author: Canner Team
Author-email: contact@cannerdata.com
License: Apache 2.0
Requires-Python: >=3.0.0
